file_parser_sdk/__init__.py
file_parser_sdk/enums/FilterType.py
file_parser_sdk/enums/LogLevel.py
file_parser_sdk/enums/ParsedDataResponseType.py
file_parser_sdk/exceptions/expcetion.py
file_parser_sdk/service/file_parser.py
file_parser_sdk/utils/common_utils.py
file_parser_sdk/utils/file_parser_constants.py
file_parser_sdk/utils/logger.py
file_parser_sdk/utils/mt940_utils.py
file_parser_sdk/utils/s3_file_parser.py
file_parser_sdk-0.3.2.dist-info/METADATA
file_parser_sdk-0.3.2.dist-info/WHEEL
file_parser_sdk-0.3.2.dist-info/top_level.txt
file_parser_sdk-0.3.2.dist-info/RECORD
